client_script
