Metadata-Version: 1.1
Name: edmunds-hdfs-load
Version: 4.0.1
Summary: Moves files to hdfs by creating hive tables
Home-page: UNKNOWN
Author: Sam Shuster
Author-email: sshuster@edmunds.com
License: None
Keywords: hive,hdfs
Platform: UNKNOWN
Classifier: Development Status :: 4 - Beta
Classifier: Topic :: Utilities
